{
  "chapterId": "eds-ch02-the-lifecycle-framework",
  "shardIndex": 1,
  "cards": [
    {
      "id": "eds-ch02-c001",
      "order": 1,
      "title": "Five Stages, One Pipeline",
      "teaser": "Every data pipeline — batch or streaming, simple or sprawling — moves through five stages. Naming them gives you a vocabulary to design and debug at the right altitude.",
      "explanation": [
        {
          "type": "paragraph",
          "runs": [
            {
              "text": "Whatever your stack, your data is doing one of five things at any moment:"
            }
          ]
        },
        {
          "type": "list",
          "style": "numbered",
          "items": [
            [
              {
                "text": "Generation",
                "marks": [
                  "bold"
                ]
              },
              {
                "text": " — being produced by an upstream system (an app, a sensor, a log emitter)."
              }
            ],
            [
              {
                "text": "Storage",
                "marks": [
                  "bold"
                ]
              },
              {
                "text": " — sitting in a place addressable for retrieval (a database, a lake, a warehouse, a queue)."
              }
            ],
            [
              {
                "text": "Ingestion",
                "marks": [
                  "bold"
                ]
              },
              {
                "text": " — moving from where it was produced to where you can use it."
              }
            ],
            [
              {
                "text": "Transformation",
                "marks": [
                  "bold"
                ]
              },
              {
                "text": " — being reshaped, joined, deduplicated, modeled."
              }
            ],
            [
              {
                "text": "Serving",
                "marks": [
                  "bold"
                ]
              },
              {
                "text": " — being made available to a consumer (analyst, model, dashboard, downstream service)."
              }
            ]
          ]
        },
        {
          "type": "paragraph",
          "runs": [
            {
              "text": "Storage spans the whole picture — data sits somewhere at every stage. Ingestion, transformation, and serving each act on that storage. Generation is the only stage you don't fully own, which is what makes it the most likely source of surprise."
            }
          ]
        },
        {
          "type": "callout",
          "variant": "info",
          "runs": [
            {
              "text": "When you're triaging a broken pipeline, name the stage first. \"Where in the lifecycle is this failing?\" cuts the search space faster than any tool-specific debugging."
            }
          ]
        }
      ],
      "feynman": [
        {
          "type": "paragraph",
          "runs": [
            {
              "text": "Like the request lifecycle of an HTTP server — accept, parse, route, handle, respond. Naming the steps lets you debug the right one."
            }
          ]
        }
      ]
    },
    {
      "id": "eds-ch02-c002",
      "order": 2,
      "title": "Generation Is What You Don't Control",
      "teaser": "Source systems produce the data you depend on, and they were almost never designed for you. That asymmetry shapes every decision downstream.",
      "explanation": [
        {
          "type": "paragraph",
          "runs": [
            {
              "text": "Generation is the lifecycle stage you observe but don't own. Upstream systems were designed for their own purposes — running an app, running a business, recording a transaction. Their schemas, their availability, their semantics all serve their primary job, not yours."
            }
          ]
        },
        {
          "type": "paragraph",
          "runs": [
            {
              "text": "This creates persistent friction:"
            }
          ]
        },
        {
          "type": "list",
          "style": "bulleted",
          "items": [
            [
              {
                "text": "Schema changes",
                "marks": [
                  "bold"
                ]
              },
              {
                "text": " without notice — a column renamed, a field deprecated, a new nullable column added that breaks your assumptions."
              }
            ],
            [
              {
                "text": "Semantic drift",
                "marks": [
                  "bold"
                ]
              },
              {
                "text": " — what "
              },
              {
                "text": "status = 'active'",
                "marks": [
                  "code"
                ]
              },
              {
                "text": " means changes when product launches a new feature."
              }
            ],
            [
              {
                "text": "Outages",
                "marks": [
                  "bold"
                ]
              },
              {
                "text": " — the source goes down and your pipeline stops, often without you noticing."
              }
            ],
            [
              {
                "text": "Volume spikes",
                "marks": [
                  "bold"
                ]
              },
              {
                "text": " — a marketing push triples the rate of new rows and your ingestion can't keep up."
              }
            ]
          ]
        },
        {
          "type": "paragraph",
          "runs": [
            {
              "text": "The data engineer's job at this stage is mostly "
            },
            {
              "text": "sensing",
              "marks": [
                "italic"
              ]
            },
            {
              "text": ": observability into the source, alerting when shape or rate or quality changes, contracts (formal or informal) with upstream teams about what they'll preserve."
            }
          ]
        },
        {
          "type": "callout",
          "variant": "warning",
          "runs": [
            {
              "text": "Pipelines that assume the source is stable will surprise you. Pipelines that assume the source is unstable will degrade gracefully. Build for the second."
            }
          ]
        }
      ],
      "feynman": [
        {
          "type": "paragraph",
          "runs": [
            {
              "text": "Like a downstream service consuming someone else's API. You're at the mercy of their changelog, so you instrument the seam."
            }
          ]
        }
      ]
    },
    {
      "id": "eds-ch02-c003",
      "order": 3,
      "title": "Storage Is The Backbone Of Everything Else",
      "teaser": "Storage isn't a stage you pass through — it's the layer everything else stands on. Picking the wrong storage shape is the most expensive mistake at lifecycle scale.",
      "explanation": [
        {
          "type": "paragraph",
          "runs": [
            {
              "text": "The other lifecycle stages — ingestion, transformation, serving — are verbs operating on storage. Storage is the noun underneath all of them."
            }
          ]
        },
        {
          "type": "paragraph",
          "runs": [
            {
              "text": "What \"storage\" actually means varies by stage and use:"
            }
          ]
        },
        {
          "type": "list",
          "style": "bulleted",
          "items": [
            [
              {
                "text": "Source storage",
                "marks": [
                  "bold"
                ]
              },
              {
                "text": " — the operational database or filesystem that holds the data when it's born."
              }
            ],
            [
              {
                "text": "Raw landing zone",
                "marks": [
                  "bold"
                ]
              },
              {
                "text": " — the first place ingested data hits in your system, often a lake."
              }
            ],
            [
              {
                "text": "Staging / curated layers",
                "marks": [
                  "bold"
                ]
              },
              {
                "text": " — refined data ready for transformation."
              }
            ],
            [
              {
                "text": "Warehouse / mart",
                "marks": [
                  "bold"
                ]
              },
              {
                "text": " — modeled, query-optimized storage for analytics."
              }
            ],
            [
              {
                "text": "Feature store",
                "marks": [
                  "bold"
                ]
              },
              {
                "text": " — engineered features ready for ML training and serving."
              }
            ],
            [
              {
                "text": "Cache / serving layer",
                "marks": [
                  "bold"
                ]
              },
              {
                "text": " — fast-read storage for application-facing consumers."
              }
            ]
          ]
        },
        {
          "type": "paragraph",
          "runs": [
            {
              "text": "The same byte may pass through three or four of these forms. Each layer has its own access patterns, retention rules, cost shape, and update semantics. Picking storage well — at each layer — is the single highest-leverage architectural decision."
            }
          ]
        },
        {
          "type": "callout",
          "variant": "tip",
          "runs": [
            {
              "text": "When a project starts with \"we already use X for storage, what should we build on top?\" you're optimizing within constraints. When you can pick the storage shape per layer, you're doing data engineering with full degrees of freedom."
            }
          ]
        }
      ],
      "feynman": [
        {
          "type": "paragraph",
          "runs": [
            {
              "text": "Same role as memory in a CPU — the speed and shape of memory shapes everything the processor can do."
            }
          ]
        }
      ]
    },
    {
      "id": "eds-ch02-c004",
      "order": 4,
      "title": "Ingestion Bridges Source And Storage",
      "teaser": "Getting data from where it's born to where you can use it sounds easy and is the source of most pipeline incidents. The patterns you choose here ripple through everything downstream.",
      "explanation": [
        {
          "type": "paragraph",
          "runs": [
            {
              "text": "Ingestion is the transit layer between generation and storage. Its core decisions:"
            }
          ]
        },
        {
          "type": "list",
          "style": "bulleted",
          "items": [
            [
              {
                "text": "Batch or streaming",
                "marks": [
                  "bold"
                ]
              },
              {
                "text": " — pull rows on a schedule, or consume events as they happen."
              }
            ],
            [
              {
                "text": "Push or pull",
                "marks": [
                  "bold"
                ]
              },
              {
                "text": " — does the source emit to you, or do you fetch from the source?"
              }
            ],
            [
              {
                "text": "Full or incremental",
                "marks": [
                  "bold"
                ]
              },
              {
                "text": " — re-load everything each time, or only what's new since last run?"
              }
            ],
            [
              {
                "text": "Sync or async",
                "marks": [
                  "bold"
                ]
              },
              {
                "text": " — does the upstream wait for ack, or fire-and-forget?"
              }
            ]
          ]
        },
        {
          "type": "paragraph",
          "runs": [
            {
              "text": "Each decision is a tradeoff. Batch is simpler and cheaper; streaming is more current and more complex. Pull gives you control over rate; push reduces latency. Incremental is efficient but requires you to track state; full is expensive but trivially correct."
            }
          ]
        },
        {
          "type": "paragraph",
          "runs": [
            {
              "text": "The most expensive ingestion mistakes are:"
            }
          ]
        },
        {
          "type": "list",
          "style": "bulleted",
          "items": [
            [
              {
                "text": "Coupling",
                "marks": [
                  "bold"
                ]
              },
              {
                "text": " — when ingestion logic leaks business semantics, you can't replay or rebuild without the original source."
              }
            ],
            [
              {
                "text": "Loss",
                "marks": [
                  "bold"
                ]
              },
              {
                "text": " — exactly-once semantics is hard; at-least-once with downstream idempotency is the realistic goal."
              }
            ],
            [
              {
                "text": "Backpressure",
                "marks": [
                  "bold"
                ]
              },
              {
                "text": " — when downstream can't keep up, ingestion needs to fail safely, not silently drop."
              }
            ]
          ]
        },
        {
          "type": "callout",
          "variant": "info",
          "runs": [
            {
              "text": "Ingestion is the lifecycle stage that most often pages someone at 3am. Invest in observability and replayability here before anywhere else."
            }
          ]
        }
      ],
      "feynman": [
        {
          "type": "paragraph",
          "runs": [
            {
              "text": "Like the import step of a build pipeline — fail loudly here or pay later."
            }
          ]
        }
      ]
    },
    {
      "id": "eds-ch02-c005",
      "order": 5,
      "title": "Transformation Turns Raw Into Useful",
      "teaser": "Raw data is rarely directly usable. Transformation is where you join, clean, model, and shape it into the artifacts that downstream consumers actually want.",
      "explanation": [
        {
          "type": "paragraph",
          "runs": [
            {
              "text": "Transformation covers everything that happens between \"data sitting in raw form\" and \"data ready for someone to query or train on.\" That includes:"
            }
          ]
        },
        {
          "type": "list",
          "style": "bulleted",
          "items": [
            [
              {
                "text": "Cleaning",
                "marks": [
                  "bold"
                ]
              },
              {
                "text": " — null handling, type coercion, deduplication, standardizing values."
              }
            ],
            [
              {
                "text": "Joining",
                "marks": [
                  "bold"
                ]
              },
              {
                "text": " — combining data from multiple sources to produce richer entities."
              }
            ],
            [
              {
                "text": "Aggregating",
                "marks": [
                  "bold"
                ]
              },
              {
                "text": " — computing summaries, metrics, rollups."
              }
            ],
            [
              {
                "text": "Modeling",
                "marks": [
                  "bold"
                ]
              },
              {
                "text": " — shaping data into business entities (customer, order, session) the rest of the org can reason about."
              }
            ],
            [
              {
                "text": "Enriching",
                "marks": [
                  "bold"
                ]
              },
              {
                "text": " — adding derived fields, lookups, geocoded values, ML-inferred attributes."
              }
            ]
          ]
        },
        {
          "type": "paragraph",
          "runs": [
            {
              "text": "The architectural choice that matters most: "
            },
            {
              "text": "where",
              "marks": [
                "bold"
              ]
            },
            {
              "text": " transformation happens."
            }
          ]
        },
        {
          "type": "list",
          "style": "bulleted",
          "items": [
            [
              {
                "text": "In the source",
                "marks": [
                  "bold"
                ]
              },
              {
                "text": " — risky; couples your needs to upstream code."
              }
            ],
            [
              {
                "text": "In flight (during ingestion)",
                "marks": [
                  "bold"
                ]
              },
              {
                "text": " — fast, but hard to recompute."
              }
            ],
            [
              {
                "text": "At rest in the warehouse (ELT)",
                "marks": [
                  "bold"
                ]
              },
              {
                "text": " — modern default; cheap compute, easy to recompute."
              }
            ],
            [
              {
                "text": "At read time (views, virtual layers)",
                "marks": [
                  "bold"
                ]
              },
              {
                "text": " — most flexible, often slowest."
              }
            ]
          ]
        },
        {
          "type": "paragraph",
          "runs": [
            {
              "text": "The shift from ETL to ELT over the past decade is largely the realization that warehouse compute became cheap enough that you can afford to land raw and transform later — preserving optionality at the cost of some warehouse spend."
            }
          ]
        },
        {
          "type": "callout",
          "variant": "tip",
          "runs": [
            {
              "text": "Keep the raw landing zone immutable. Transformation should be reproducible from the raw — that's how you regain confidence after a logic bug."
            }
          ]
        }
      ],
      "feynman": [
        {
          "type": "paragraph",
          "runs": [
            {
              "text": "Same as a build step in code — start from source, produce the artifacts other systems consume."
            }
          ]
        }
      ]
    },
    {
      "id": "eds-ch02-c006",
      "order": 6,
      "title": "Serving Closes The Loop",
      "teaser": "Data that's been generated, ingested, stored, and transformed still has zero value until it reaches a consumer. Serving is the stage where business value finally crystallizes.",
      "explanation": [
        {
          "type": "paragraph",
          "runs": [
            {
              "text": "Serving is the lifecycle's payoff. Three primary serving patterns:"
            }
          ]
        },
        {
          "type": "list",
          "style": "bulleted",
          "items": [
            [
              {
                "text": "Analytics serving",
                "marks": [
                  "bold"
                ]
              },
              {
                "text": " — humans querying data for decisions. Dashboards, BI tools, ad-hoc SQL. The latency budget is \"as fast as a curious analyst can stand.\""
              }
            ],
            [
              {
                "text": "ML serving",
                "marks": [
                  "bold"
                ]
              },
              {
                "text": " — models consuming data, either for training (large batches) or inference (single-row reads at serving time). Feature stores live here."
              }
            ],
            [
              {
                "text": "Reverse ETL",
                "marks": [
                  "bold"
                ]
              },
              {
                "text": " — operational systems consuming the warehouse's curated data. The CRM gets enriched customer attributes; the support tool gets account health scores; the marketing platform gets segments."
              }
            ]
          ]
        },
        {
          "type": "paragraph",
          "runs": [
            {
              "text": "Each pattern has distinct access shape:"
            }
          ]
        },
        {
          "type": "list",
          "style": "bulleted",
          "items": [
            [
              {
                "text": "Analytics — large scans, low concurrency, columnar storage wins."
              }
            ],
            [
              {
                "text": "ML training — large reads, often sequential, format matters (parquet, TFRecord)."
              }
            ],
            [
              {
                "text": "ML inference — point reads, single-digit-ms latency, key-value or in-memory shape."
              }
            ],
            [
              {
                "text": "Reverse ETL — incremental syncs back into operational systems, often via CDC."
              }
            ]
          ]
        },
        {
          "type": "paragraph",
          "runs": [
            {
              "text": "The serving layer often dictates the shape of the rest of the lifecycle. Build it last as an afterthought and you'll redo earlier stages to support it."
            }
          ]
        },
        {
          "type": "callout",
          "variant": "warning",
          "runs": [
            {
              "text": "If serving requirements aren't clear when you start designing the lifecycle, your design will optimize for what's easy to build instead of what's needed."
            }
          ]
        }
      ],
      "feynman": [
        {
          "type": "paragraph",
          "runs": [
            {
              "text": "Same as the response of an HTTP service — everything before exists to make this moment fast and correct."
            }
          ]
        }
      ]
    },
    {
      "id": "eds-ch02-c007",
      "order": 7,
      "title": "Undercurrents — The Cross-Cutting Concerns",
      "teaser": "Six concerns run beneath every lifecycle stage. Get them wrong and the whole pipeline degrades, no matter how nicely each stage is built.",
      "explanation": [
        {
          "type": "paragraph",
          "runs": [
            {
              "text": "The lifecycle stages explain the "
            },
            {
              "text": "flow",
              "marks": [
                "italic"
              ]
            },
            {
              "text": " of data. The undercurrents explain the "
            },
            {
              "text": "concerns",
              "marks": [
                "italic"
              ]
            },
            {
              "text": " that touch every stage. The six in the framework:"
            }
          ]
        },
        {
          "type": "list",
          "style": "numbered",
          "items": [
            [
              {
                "text": "Security",
                "marks": [
                  "bold"
                ]
              },
              {
                "text": " — auth, authz, encryption, key management, threat modeling."
              }
            ],
            [
              {
                "text": "Data management",
                "marks": [
                  "bold"
                ]
              },
              {
                "text": " — quality, governance, lineage, master data, MDM."
              }
            ],
            [
              {
                "text": "DataOps",
                "marks": [
                  "bold"
                ]
              },
              {
                "text": " — automation, observability, incident response for data systems."
              }
            ],
            [
              {
                "text": "Data architecture",
                "marks": [
                  "bold"
                ]
              },
              {
                "text": " — the design discipline that ties stages together coherently."
              }
            ],
            [
              {
                "text": "Orchestration",
                "marks": [
                  "bold"
                ]
              },
              {
                "text": " — scheduling, dependency management, retry policy across pipelines."
              }
            ],
            [
              {
                "text": "Software engineering",
                "marks": [
                  "bold"
                ]
              },
              {
                "text": " — testing, version control, code review, modularity, all the boring excellence that makes data work production-grade."
              }
            ]
          ]
        },
        {
          "type": "paragraph",
          "runs": [
            {
              "text": "Every lifecycle stage touches every undercurrent. Generation needs security and governance. Ingestion needs orchestration and DataOps. Transformation needs software engineering. Serving needs all six."
            }
          ]
        },
        {
          "type": "paragraph",
          "runs": [
            {
              "text": "Treating undercurrents as \"nice to have, later\" is the most common path to expensive cleanup years down the line."
            }
          ]
        },
        {
          "type": "callout",
          "variant": "tip",
          "runs": [
            {
              "text": "When evaluating a new tool, ask not just \"what stage does it serve?\" but \"how well does it support each undercurrent?\" The latter often distinguishes great tools from merely-shippable ones."
            }
          ]
        }
      ],
      "feynman": [
        {
          "type": "paragraph",
          "runs": [
            {
              "text": "Like cross-cutting concerns in software — logging, security, monitoring. Touches every layer; missing it costs you the whole stack."
            }
          ]
        }
      ]
    },
    {
      "id": "eds-ch02-c008",
      "order": 8,
      "title": "Security Touches Every Stage",
      "teaser": "Data is one of the most valuable and most attacked assets a company has. Security in data systems is not a stage — it's a permanent posture.",
      "explanation": [
        {
          "type": "paragraph",
          "runs": [
            {
              "text": "Security as an undercurrent means at every lifecycle stage you're answering:"
            }
          ]
        },
        {
          "type": "list",
          "style": "bulleted",
          "items": [
            [
              {
                "text": "Who can access this data?",
                "marks": [
                  "bold"
                ]
              },
              {
                "text": " — IAM, role-based access, attribute-based access."
              }
            ],
            [
              {
                "text": "How is it protected at rest?",
                "marks": [
                  "bold"
                ]
              },
              {
                "text": " — disk-level encryption, field-level encryption for sensitive columns."
              }
            ],
            [
              {
                "text": "How is it protected in transit?",
                "marks": [
                  "bold"
                ]
              },
              {
                "text": " — TLS everywhere, signed payloads, mutual auth between services."
              }
            ],
            [
              {
                "text": "Who has touched it, and when?",
                "marks": [
                  "bold"
                ]
              },
              {
                "text": " — audit logging, data access logs, immutable trails."
              }
            ],
            [
              {
                "text": "Where is it allowed to physically live?",
                "marks": [
                  "bold"
                ]
              },
              {
                "text": " — sovereignty, residency, regulatory boundaries."
              }
            ],
            [
              {
                "text": "How quickly can we delete it?",
                "marks": [
                  "bold"
                ]
              },
              {
                "text": " — for GDPR, CCPA, contractual obligations."
              }
            ]
          ]
        },
        {
          "type": "paragraph",
          "runs": [
            {
              "text": "The principle of least privilege belongs in data systems too: no one and no service has more access than they need to do their job. Default access broad and tighten later is the path to regulatory pain."
            }
          ]
        },
        {
          "type": "callout",
          "variant": "warning",
          "runs": [
            {
              "text": "Data engineers are often the first responders to data breaches in their organizations. Build the audit trail before you need it — recovering history after the fact is rarely possible."
            }
          ]
        }
      ],
      "feynman": [
        {
          "type": "paragraph",
          "runs": [
            {
              "text": "Like memory safety in a language — not a feature you add later, a property you preserve from the start."
            }
          ]
        }
      ]
    },
    {
      "id": "eds-ch02-c009",
      "order": 9,
      "title": "Data Management Means Treating Data Like A Product",
      "teaser": "Data management is the discipline of running data as a curated, governed, documented asset rather than a side-effect of operations.",
      "explanation": [
        {
          "type": "paragraph",
          "runs": [
            {
              "text": "Data management as an undercurrent covers the practices that turn raw data into a reliable product for downstream consumers:"
            }
          ]
        },
        {
          "type": "list",
          "style": "bulleted",
          "items": [
            [
              {
                "text": "Quality",
                "marks": [
                  "bold"
                ]
              },
              {
                "text": " — completeness, accuracy, freshness, consistency. Tested, monitored, alerted."
              }
            ],
            [
              {
                "text": "Lineage",
                "marks": [
                  "bold"
                ]
              },
              {
                "text": " — knowing which sources feed which tables feed which dashboards. When something looks wrong, you can trace it backward."
              }
            ],
            [
              {
                "text": "Governance",
                "marks": [
                  "bold"
                ]
              },
              {
                "text": " — agreed-on definitions, ownership, change processes, deprecation policies."
              }
            ],
            [
              {
                "text": "Master data management",
                "marks": [
                  "bold"
                ]
              },
              {
                "text": " — single sources of truth for the entities that matter (customer, product, employee)."
              }
            ],
            [
              {
                "text": "Metadata",
                "marks": [
                  "bold"
                ]
              },
              {
                "text": " — schema definitions, descriptions, ownership, tags, business glossary."
              }
            ],
            [
              {
                "text": "Catalog",
                "marks": [
                  "bold"
                ]
              },
              {
                "text": " — a searchable, browsable inventory of what data exists and where."
              }
            ]
          ]
        },
        {
          "type": "paragraph",
          "runs": [
            {
              "text": "A team strong on data management produces datasets analysts trust enough to build dashboards on without asking. A team weak on data management produces datasets every consumer reverifies independently — a tax that compounds."
            }
          ]
        },
        {
          "type": "callout",
          "variant": "info",
          "runs": [
            {
              "text": "The data mesh movement is largely an organizational answer to data management at scale: treat data as a product, with a product team that owns it."
            }
          ]
        }
      ],
      "feynman": [
        {
          "type": "paragraph",
          "runs": [
            {
              "text": "Same as treating an internal API as a product — versioning, docs, support, deprecation. Or skip those and watch your consumers go elsewhere."
            }
          ]
        }
      ]
    },
    {
      "id": "eds-ch02-c010",
      "order": 10,
      "title": "DataOps Brings DevOps Discipline To Pipelines",
      "teaser": "DataOps is what happens when DevOps practices land in the data world: automation, observability, incident response, and continuous delivery for data pipelines.",
      "explanation": [
        {
          "type": "paragraph",
          "runs": [
            {
              "text": "DataOps takes the cultural and tooling wins of DevOps and applies them to data systems. The key practices:"
            }
          ]
        },
        {
          "type": "list",
          "style": "bulleted",
          "items": [
            [
              {
                "text": "Automation",
                "marks": [
                  "bold"
                ]
              },
              {
                "text": " — pipelines deployed, tested, and rolled back like any other code."
              }
            ],
            [
              {
                "text": "CI/CD for data",
                "marks": [
                  "bold"
                ]
              },
              {
                "text": " — schema changes go through PR, dbt models get tested before they merge, ingestion code ships through pipelines."
              }
            ],
            [
              {
                "text": "Observability",
                "marks": [
                  "bold"
                ]
              },
              {
                "text": " — pipeline runs, freshness, row counts, schema drift, all instrumented and dashboarded."
              }
            ],
            [
              {
                "text": "Incident response",
                "marks": [
                  "bold"
                ]
              },
              {
                "text": " — on-call for data, alerting tied to user-impacting metrics, postmortems for data outages."
              }
            ],
            [
              {
                "text": "Collaboration",
                "marks": [
                  "bold"
                ]
              },
              {
                "text": " — data engineers, analytics engineers, analysts, and consumers in shared communication and shared ownership."
              }
            ]
          ]
        },
        {
          "type": "paragraph",
          "runs": [
            {
              "text": "The cultural shift is harder than the technical one. Data teams historically operated more like research labs than software teams. DataOps drags them — productively — toward the engineering discipline software teams already accept as table stakes."
            }
          ]
        },
        {
          "type": "callout",
          "variant": "tip",
          "runs": [
            {
              "text": "Adopt CI for dbt or your equivalent transformation tool first. The rest of DataOps tends to follow once your team feels the win."
            }
          ]
        }
      ],
      "feynman": [
        {
          "type": "paragraph",
          "runs": [
            {
              "text": "Same maturity arc as DevOps a decade ago — manual deploys to pipelines to immutable infrastructure. Took years; the wins compound forever."
            }
          ]
        }
      ]
    },
    {
      "id": "eds-ch02-c011",
      "order": 11,
      "title": "Data Architecture Is The Glue",
      "teaser": "Architecture is the discipline of designing how stages connect coherently — boundaries, interfaces, technologies, and the trade-offs you accept on purpose.",
      "explanation": [
        {
          "type": "paragraph",
          "runs": [
            {
              "text": "Data architecture as an undercurrent is the practice of designing the system as a system, not as a collection of pipelines. Key responsibilities:"
            }
          ]
        },
        {
          "type": "list",
          "style": "bulleted",
          "items": [
            [
              {
                "text": "Stage boundaries",
                "marks": [
                  "bold"
                ]
              },
              {
                "text": " — what's owned by ingestion, what's owned by transformation, what's owned by serving. Where one ends and the next begins."
              }
            ],
            [
              {
                "text": "Technology choices",
                "marks": [
                  "bold"
                ]
              },
              {
                "text": " — picking warehouse, lake, orchestrator, ingestion tools, BI in a way that composes well."
              }
            ],
            [
              {
                "text": "Patterns vs anti-patterns",
                "marks": [
                  "bold"
                ]
              },
              {
                "text": " — knowing the canonical solution for common shapes (CDC for ops-to-analytics, lambda for batch+stream, lakehouse for cheap-storage-with-warehouse-semantics)."
              }
            ],
            [
              {
                "text": "Future-proofing",
                "marks": [
                  "bold"
                ]
              },
              {
                "text": " — making architectural decisions that survive the next reorg or vendor change."
              }
            ]
          ]
        },
        {
          "type": "paragraph",
          "runs": [
            {
              "text": "A team without explicit data architecture grows by accretion: every new pipeline reaches for whatever was nearest, and you wake up two years later with three orchestrators, four ingestion tools, and warehouses in two clouds. Untangling that costs more than designing it well in the first place."
            }
          ]
        },
        {
          "type": "callout",
          "variant": "info",
          "runs": [
            {
              "text": "The architect role on a data team is often part-time — the most senior engineer reserving 20% of their week for architectural decisions, design reviews, and rejection of expedient choices."
            }
          ]
        }
      ],
      "feynman": [
        {
          "type": "paragraph",
          "runs": [
            {
              "text": "Same as software architecture — the load-bearing decisions that make subsequent decisions easier or harder."
            }
          ]
        }
      ]
    },
    {
      "id": "eds-ch02-c012",
      "order": 12,
      "title": "Orchestration Schedules And Sequences The Work",
      "teaser": "Orchestration is the layer that decides when each piece of the lifecycle runs, in what order, and what happens when something goes wrong.",
      "explanation": [
        {
          "type": "paragraph",
          "runs": [
            {
              "text": "A pipeline isn't one job — it's many jobs with dependencies. Orchestration is what runs them in the right order, retries them when they fail, and tells you when something stuck."
            }
          ]
        },
        {
          "type": "paragraph",
          "runs": [
            {
              "text": "What an orchestrator does:"
            }
          ]
        },
        {
          "type": "list",
          "style": "bulleted",
          "items": [
            [
              {
                "text": "Schedule",
                "marks": [
                  "bold"
                ]
              },
              {
                "text": " — fire jobs on time-based or event-based triggers."
              }
            ],
            [
              {
                "text": "Sequence",
                "marks": [
                  "bold"
                ]
              },
              {
                "text": " — express dependencies as a DAG; downstream jobs wait for upstream to finish."
              }
            ],
            [
              {
                "text": "Retry",
                "marks": [
                  "bold"
                ]
              },
              {
                "text": " — failed jobs get retried with backoff, often with state preserved."
              }
            ],
            [
              {
                "text": "Observability",
                "marks": [
                  "bold"
                ]
              },
              {
                "text": " — runs, durations, statuses, logs all visible in one place."
              }
            ],
            [
              {
                "text": "Backfill",
                "marks": [
                  "bold"
                ]
              },
              {
                "text": " — re-run pipelines for historical periods to recover from bugs or data gaps."
              }
            ]
          ]
        },
        {
          "type": "paragraph",
          "runs": [
            {
              "text": "Modern options span Airflow (the legacy default), Prefect, Dagster (data-aware), Argo (Kubernetes-native), Temporal (general-purpose workflow engine), and managed services from each cloud. Picking poorly here is one of the more painful migrations later."
            }
          ]
        },
        {
          "type": "callout",
          "variant": "warning",
          "runs": [
            {
              "text": "Crontab + bash scripts is technically orchestration. It scales until it doesn't — usually right around the point you have 30 jobs and a junior engineer trying to debug why Tuesday's data is missing."
            }
          ]
        }
      ],
      "feynman": [
        {
          "type": "paragraph",
          "runs": [
            {
              "text": "Like systemd or a job scheduler — figures out what to run, in what order, and what to do when things break."
            }
          ]
        }
      ]
    },
    {
      "id": "eds-ch02-c013",
      "order": 13,
      "title": "Software Engineering Is The Quiet Multiplier",
      "teaser": "Treating data pipelines like real software — version controlled, tested, modular, reviewed — separates teams that scale from teams that drown.",
      "explanation": [
        {
          "type": "paragraph",
          "runs": [
            {
              "text": "The software engineering undercurrent is the discipline of running data work like the production software it has become. The basics:"
            }
          ]
        },
        {
          "type": "list",
          "style": "bulleted",
          "items": [
            [
              {
                "text": "Version control everything",
                "marks": [
                  "bold"
                ]
              },
              {
                "text": " — pipeline code, SQL, configs, infrastructure-as-code, even dashboard definitions where possible."
              }
            ],
            [
              {
                "text": "Test pipelines",
                "marks": [
                  "bold"
                ]
              },
              {
                "text": " — unit-test transformations, integration-test end-to-end runs, contract-test schemas."
              }
            ],
            [
              {
                "text": "Code review",
                "marks": [
                  "bold"
                ]
              },
              {
                "text": " — every change touched by another engineer before it lands."
              }
            ],
            [
              {
                "text": "Modularity",
                "marks": [
                  "bold"
                ]
              },
              {
                "text": " — small, well-named, single-purpose components that compose. Avoid the 2000-line stored procedure."
              }
            ],
            [
              {
                "text": "Documentation",
                "marks": [
                  "bold"
                ]
              },
              {
                "text": " — runbooks, READMEs, architecture diagrams that match reality."
              }
            ],
            [
              {
                "text": "Refactoring",
                "marks": [
                  "bold"
                ]
              },
              {
                "text": " — periodically pay down complexity instead of accumulating it forever."
              }
            ]
          ]
        },
        {
          "type": "paragraph",
          "runs": [
            {
              "text": "Data teams that absorb these practices ship faster with fewer outages within a year. Data teams that resist them tend to feel busy without producing reliable systems."
            }
          ]
        },
        {
          "type": "callout",
          "variant": "tip",
          "runs": [
            {
              "text": "If your team's transformation code lives in the warehouse UI rather than version control, the migration to git pays off in months. It's the single most leveraged operational change you can make."
            }
          ]
        }
      ],
      "feynman": [
        {
          "type": "paragraph",
          "runs": [
            {
              "text": "Same lessons software engineering learned 30 years ago. Data work is software work; treat it like one."
            }
          ]
        }
      ]
    },
    {
      "id": "eds-ch02-c014",
      "order": 14,
      "title": "Putting It Together",
      "teaser": "The lifecycle gives you the flow; the undercurrents give you the cross-cutting concerns. Together they form the structure for every chapter that follows.",
      "explanation": [
        {
          "type": "paragraph",
          "runs": [
            {
              "text": "The framework you'll see referenced through the rest of the book:"
            }
          ]
        },
        {
          "type": "code",
          "language": "",
          "code": "                    ┌─────────────────────────────────────────┐\n   GENERATION ───▶  │                                         │\n                    │  STORAGE ◀── INGESTION ── TRANSFORM     │  ───▶ SERVING\n                    │     ▲                                   │\n                    └─────│───────────────────────────────────┘\n                          │\n                          │  Undercurrents (touch every stage)\n                          │\n                          ├─ Security\n                          ├─ Data Management\n                          ├─ DataOps\n                          ├─ Data Architecture\n                          ├─ Orchestration\n                          └─ Software Engineering"
        },
        {
          "type": "paragraph",
          "runs": [
            {
              "text": "Each remaining chapter zooms in:"
            }
          ]
        },
        {
          "type": "list",
          "style": "bulleted",
          "items": [
            [
              {
                "text": "Chapter 3",
                "marks": [
                  "bold"
                ]
              },
              {
                "text": " — designing architecture across the lifecycle."
              }
            ],
            [
              {
                "text": "Chapter 4",
                "marks": [
                  "bold"
                ]
              },
              {
                "text": " — choosing technology for each stage."
              }
            ],
            [
              {
                "text": "Chapters 5-9",
                "marks": [
                  "bold"
                ]
              },
              {
                "text": " — generation, storage, ingestion, transformation, serving in depth."
              }
            ],
            [
              {
                "text": "Chapter 10",
                "marks": [
                  "bold"
                ]
              },
              {
                "text": " — security and privacy as cross-cutting practice."
              }
            ],
            [
              {
                "text": "Chapter 11",
                "marks": [
                  "bold"
                ]
              },
              {
                "text": " — where the field is heading."
              }
            ]
          ]
        },
        {
          "type": "paragraph",
          "runs": [
            {
              "text": "If you only remember one thing from this chapter: name the lifecycle stage and the relevant undercurrents whenever you're designing or debugging. That single habit raises the quality of decisions across the whole job."
            }
          ]
        },
        {
          "type": "callout",
          "variant": "info",
          "runs": [
            {
              "text": "You'll see this same diagram, with different stages annotated, throughout the book. The framework is the spine; everything else hangs off it."
            }
          ]
        }
      ],
      "feynman": [
        {
          "type": "paragraph",
          "runs": [
            {
              "text": "Like a periodic table for data work — once you have the structure, you can reason about elements you haven't seen yet."
            }
          ]
        }
      ]
    }
  ]
}